fluffy_code/__init__.py
fluffy_code/code.py
fluffy_code/prebuilt_styles.py
fluffy_code/py.typed
fluffy_code/static/__init__.py
fluffy_code/static/global.css
fluffy_code/static/global.js
fluffy_code/style.py
fluffy_code-0.0.2.dist-info/WHEEL
fluffy_code-0.0.2.dist-info/METADATA
fluffy_code-0.0.2.dist-info/RECORD
