Metadata-Version: 2.1
Name: fluffy-code
Version: 0.0.2
Summary: A developer-friendly code rendering library for Python web applications
License: Apache-2.0
Author: Chris Kuehl
Author-email: ckuehl@ckuehl.me
Requires-Python: >=3.7,<4.0
Classifier: License :: OSI Approved :: Apache Software License
Classifier: Programming Language :: Python :: 3
Classifier: Programming Language :: Python :: 3.7
Classifier: Programming Language :: Python :: 3.8
Classifier: Programming Language :: Python :: 3.9
Classifier: Programming Language :: Python :: 3.10
Requires-Dist: MarkupSafe
Requires-Dist: Pygments
Requires-Dist: pygments-ansi-color
Requires-Dist: pyquery
